.supernova
LICENSE
MANIFEST.in
mkdocs.yml
setup.py
contrib/supernova-completion.bash
docs/configuring.md
docs/gettingstarted.md
docs/index.md
docs/installation.md
docs/raxquickstart.md
docs/troubleshooting.md
docs/usingsupernova.md
example_configs/supernova_rackspace
example_configs/supernova_rax_multiregion
supernova/__init__.py
supernova/config.py
supernova/credentials.py
supernova/executable.py
supernova/supernova.py
supernova/utils.py
supernova.egg-info/PKG-INFO
supernova.egg-info/SOURCES.txt
supernova.egg-info/dependency_links.txt
supernova.egg-info/entry_points.txt
supernova.egg-info/pbr.json
supernova.egg-info/requires.txt
supernova.egg-info/top_level.txt
tests/test_config.py
tests/test_credentials.py
tests/test_executable.py
tests/test_imports.py
tests/test_supernova.py
tests/test_utils.py
tests/configs/rax_with_keyring
tests/configs/rax_without_keyring
tests/configs/rax_without_keyring_malformed