Metadata-Version: 1.0
Name: supernova
Version: 2.2.0
Summary: novaclient wrapper for multiple nova environments
Home-page: https://github.com/major/supernova
Author: Major Hayden
Author-email: major@mhtx.net
License: UNKNOWN
Platform: UNKNOWN
